webcomic_publisher/cli.py
webcomic_publisher-0.1.4.dist-info/LICENSE
webcomic_publisher-0.1.4.dist-info/METADATA
webcomic_publisher-0.1.4.dist-info/WHEEL
webcomic_publisher-0.1.4.dist-info/entry_points.txt
webcomic_publisher-0.1.4.dist-info/RECORD
